{
  "Routes": [
    {
      "DownstreamPathTemplate": "/api/customer",
      "DownstreamScheme": "http",
      "DownstreamHostAndPorts": [
        {
          "Host": "localhost",
          "Port": 9001
        }
      ],
      "UpstreamPathTemplate": "/musteri-servisi/musteriler"
      //,"UpstreamHttpMethod": [ "GET" ]
    },
    {
      "DownstreamPathTemplate": "/api/marketingexpert",
      "DownstreamScheme": "http",
      "DownstreamHostAndPorts": [
        {
          "Host": "localhost",
          "Port": 9002
        }
      ],
      "UpstreamPathTemplate": "/pazarlama-servisi/pazarlama-uzmanlari"
      //,"UpstreamHttpMethod": [ "GET" ]
    }
  ],
  "GlobalConfiguration": {
    "BaseUrl": "http://localhost:9000"
  }
} 